{"default":{"identifier":"default","description":"Default capabilities for the main window","local":true,"windows":["main"],"permissions":["core:default","core:event:default","core:event:allow-emit","core:event:allow-listen","shell:allow-open","dialog:default","dialog:allow-open","dialog:allow-save","fs:default","fs:read-all","fs:write-all",{"identifier":"fs:scope","allow":[{"path":"$HOME"},{"path":"$HOME/**"}]},"global-shortcut:allow-register","global-shortcut:allow-unregister","global-shortcut:allow-is-registered"]}}